TwitterArchive/__init__.py
TwitterArchive/cli.py
TwitterArchive/core.py
twitter_archive-0.0.6.dist-info/LICENSE
twitter_archive-0.0.6.dist-info/METADATA
twitter_archive-0.0.6.dist-info/WHEEL
twitter_archive-0.0.6.dist-info/entry_points.txt
twitter_archive-0.0.6.dist-info/top_level.txt
twitter_archive-0.0.6.dist-info/RECORD
