Metadata-Version: 2.1
Name: twitter-archive
Version: 0.0.6
Summary: A CLI tool to download media from bookmarked tweets.
Author-email: Joshua Arulsamy <joshua.gf.arul@gmail.com>
Classifier: Development Status :: 3 - Alpha
Classifier: Environment :: Console
Classifier: License :: OSI Approved :: GNU General Public License v3 (GPLv3)
Classifier: Operating System :: OS Independent
Classifier: Programming Language :: Python :: 3.9
Classifier: Programming Language :: Python :: 3.10
Classifier: Programming Language :: Python :: 3 :: Only
Classifier: Topic :: System :: Archiving
Requires-Python: >=3.9
License-File: LICENSE
Requires-Dist: python-dotenv (~=0.20.0)
Requires-Dist: requests (~=2.28.1)
Requires-Dist: tqdm (~=4.64.0)
Requires-Dist: tweepy (~=4.10.0)
